example_malicious/__init__.py
example_malicious-0.0.2.dist-info/METADATA
example_malicious-0.0.2.dist-info/WHEEL
example_malicious-0.0.2.dist-info/top_level.txt
example_malicious-0.0.2.dist-info/RECORD
